lightningaddon/__init__.py
lightningaddon/general.py
lightningaddon/layers.py
lightningaddon/loss.py
lightningaddon/main.py
lightningaddon/tests.py
lightningaddon/models/__init__.py
lightningaddon/models/xresnet.py
lightningaddon-0.0.2.dist-info/METADATA
lightningaddon-0.0.2.dist-info/WHEEL
lightningaddon-0.0.2.dist-info/top_level.txt
lightningaddon-0.0.2.dist-info/RECORD
