Metadata-Version: 2.1
Name: lightningaddon
Version: 0.0.2
Summary: Add ons for pytorch lightning
Home-page: https://github.com/SubhadityaMukherjee/lightningAddOns
Author: Subhaditya Mukherjee
Author-email: msubhaditya@gmail.com
License: GPLv3+
Platform: UNKNOWN
Classifier: Programming Language :: Python :: 3
Classifier: License :: OSI Approved :: MIT License
Classifier: Operating System :: OS Independent
